langchainkit/__init__.py
langchainkit/local_vllm.py
langchainkit/structured_llm.py
langchainkit/test_prompt_parsing.py
langchainkit/utils.py
langchainkit-0.1.5.dist-info/licenses/LICENSE
langchainkit-0.1.5.dist-info/METADATA
langchainkit-0.1.5.dist-info/WHEEL
langchainkit-0.1.5.dist-info/top_level.txt
langchainkit-0.1.5.dist-info/RECORD
