Metadata-Version: 2.4
Name: langchainkit
Version: 0.1.5
Summary: LangChainKit makes it easier to work with Qwen3 models via vLLM, and simplifies the process of prompting LLMs to return structured outputs using LangChain and Langfuse.
Author-email: AInseven <your.email@example.com>
License: MIT
Project-URL: Homepage, https://github.com/AInseven/langchainkit
Project-URL: Repository, https://github.com/AInseven/langchainkit.git
Project-URL: Issues, https://github.com/AInseven/langchainkit/issues
Classifier: Development Status :: 3 - Alpha
Classifier: Intended Audience :: Developers
Classifier: License :: OSI Approved :: MIT License
Classifier: Programming Language :: Python :: 3
Classifier: Programming Language :: Python :: 3.8
Classifier: Programming Language :: Python :: 3.9
Classifier: Programming Language :: Python :: 3.10
Classifier: Programming Language :: Python :: 3.11
Classifier: Programming Language :: Python :: 3.12
Requires-Python: >=3.8
License-File: LICENSE
Requires-Dist: langchain-openai>=0.3.16
Requires-Dist: langchain-community>=0.3.23
Requires-Dist: langchain-deepseek>=0.1.3
Requires-Dist: langchain-core>=0.3.0
Requires-Dist: pydantic>=2.0.0
Requires-Dist: python-dotenv>=1.0.0
Requires-Dist: loguru>=0.7.0
Requires-Dist: langfuse>=2.0.0
Provides-Extra: dev
Requires-Dist: pytest>=7.0.0; extra == "dev"
Requires-Dist: pytest-asyncio>=0.21.0; extra == "dev"
Requires-Dist: black>=22.0.0; extra == "dev"
Requires-Dist: isort>=5.0.0; extra == "dev"
Requires-Dist: flake8>=4.0.0; extra == "dev"
Dynamic: license-file
